pyash/__init__.py
pyash/expression_already_completed_error.py
pyash/lazy_invocation.py
pyash/process_error.py
pyash-0.1.0.dist-info/LICENCE.md
pyash-0.1.0.dist-info/METADATA
pyash-0.1.0.dist-info/WHEEL
pyash-0.1.0.dist-info/top_level.txt
pyash-0.1.0.dist-info/RECORD
