Metadata-Version: 2.1
Name: pyash
Version: 0.1.0
Summary: Shell scripting... but in glorious Python! 
Home-page: https://github.com/JamJar00/pyash
Author: Jamie Read
Author-email: jamie@darkriftnetworking.com
License: UNKNOWN
Platform: UNKNOWN
Classifier: Programming Language :: Python :: 3
Classifier: License :: OSI Approved :: MIT License
Classifier: Operating System :: OS Independent
Requires-Python: >=3.6
